aioairq/__init__.py
aioairq/core.py
aioairq/encrypt.py
aioairq/exceptions.py
aioairq/utils.py
aioairq-0.4.7.dist-info/licenses/LICENSE
aioairq-0.4.7.dist-info/METADATA
aioairq-0.4.7.dist-info/WHEEL
aioairq-0.4.7.dist-info/top_level.txt
aioairq-0.4.7.dist-info/RECORD
