Metadata-Version: 2.4
Name: aioairq
Version: 0.4.7
Summary: Asynchronous library to retrieve data from air-Q devices.
Author-email: Daniel Lehmann <daniel.lehmann@air-q.com>, Renat Sibgatulin <renat.sibgatulin@air-q.com>
License: Apache License, Version 2.0
Project-URL: Homepage, https://github.com/CorantGmbH/aioairq
Project-URL: Bug Tracker, https://github.com/CorantGmbH/aioairq/issues
Classifier: Intended Audience :: Developers
Classifier: Operating System :: OS Independent
Classifier: Programming Language :: Python
Classifier: Programming Language :: Python :: 3
Classifier: Programming Language :: Python :: 3.9
Classifier: Programming Language :: Python :: 3.10
Classifier: Programming Language :: Python :: 3.11
Classifier: Programming Language :: Python :: 3.12
Classifier: Programming Language :: Python :: 3.13
Classifier: Topic :: Software Development :: Libraries :: Python Modules
Requires-Python: >=3.9
License-File: LICENSE
Requires-Dist: aiohttp
Requires-Dist: pycryptodome
Provides-Extra: dev
Requires-Dist: ruff; extra == "dev"
Requires-Dist: pre-commit; extra == "dev"
Requires-Dist: pytest; extra == "dev"
Requires-Dist: pytest-asyncio; extra == "dev"
Dynamic: license-file
